remmina_resizer
