Metadata-Version: 1.1
Name: remmina-resizer
Version: 0.0.5
Summary: A simple package for auto-adjusting rdp session resolution in Remmina connection files
Home-page: https://github.com/trondhindenes/remmina-resizer
Author: Trond Hindenes
Author-email: trond@hindenes.com
License: UNKNOWN
Download-URL: https://github.com/trondhindenes/remmina-resizer/archive/0.0.5.tar.gz
Platform: UNKNOWN
